{
  "b": 209,
  "disableInputWhenNotFocused": true,
  "mangledName": "Game_95Customisation_95WIP",
  "name": "Game_Customisation_WIP",
  "r": 209,
  "standardSortMethod": true,
  "stopSoundsOnStartup": true,
  "title": "",
  "v": 209,
  "uiSettings": {
    "grid": false,
    "gridType": "rectangular",
    "gridWidth": 32,
    "gridHeight": 32,
    "gridOffsetX": 0,
    "gridOffsetY": 0,
    "gridColor": 10401023,
    "gridAlpha": 0.8,
    "snap": false,
    "zoomFactor": 0.9679970813577352,
    "windowMask": false
  },
  "objectsGroups": [],
  "variables": [],
  "instances": [
    {
      "angle": 0,
      "customSize": false,
      "height": 0,
      "layer": "",
      "name": "player_body",
      "persistentUuid": "fe739552-1993-438f-b5b4-5c816cf15f53",
      "width": 0,
      "x": 334,
      "y": 255,
      "zOrder": 6,
      "numberProperties": [],
      "stringProperties": [],
      "initialVariables": []
    },
    {
      "angle": 0,
      "customSize": false,
      "height": 0,
      "layer": "",
      "name": "player_leg",
      "persistentUuid": "1ab6ba1f-9d01-40cc-a99c-79e52279ef47",
      "width": 0,
      "x": 337,
      "y": 195,
      "zOrder": 2,
      "numberProperties": [],
      "stringProperties": [],
      "initialVariables": []
    },
    {
      "angle": 0,
      "customSize": false,
      "height": 0,
      "layer": "",
      "name": "player_hand",
      "persistentUuid": "95d85909-f8e1-4db3-860b-07dac18c73ee",
      "width": 0,
      "x": 341,
      "y": 375,
      "zOrder": 3,
      "numberProperties": [],
      "stringProperties": [],
      "initialVariables": []
    },
    {
      "angle": 0,
      "customSize": false,
      "height": 0,
      "layer": "",
      "name": "SquareWhiteSlider",
      "persistentUuid": "57f41a4c-af1b-4264-9a44-b3e0ee2286dc",
      "width": 0,
      "x": 259,
      "y": 496,
      "zOrder": 7,
      "numberProperties": [],
      "stringProperties": [],
      "initialVariables": []
    },
    {
      "angle": 0,
      "customSize": false,
      "height": 0,
      "layer": "",
      "name": "WhiteDecoratedButton",
      "persistentUuid": "a50905bd-9ce5-4c4a-8abf-e4868197ee7b",
      "width": 0,
      "x": 697,
      "y": 487,
      "zOrder": 8,
      "numberProperties": [],
      "stringProperties": [],
      "initialVariables": []
    }
  ],
  "objects": [
    {
      "adaptCollisionMaskAutomatically": true,
      "assetStoreId": "",
      "name": "player_body",
      "type": "Sprite",
      "updateIfNotVisible": false,
      "variables": [
        {
          "folded": true,
          "name": "Animation",
          "type": "string",
          "value": ""
        },
        {
          "name": "Movement",
          "type": "structure",
          "children": [
            {
              "folded": true,
              "name": "handTweenDuration",
              "type": "number",
              "value": 0.5
            },
            {
              "folded": true,
              "name": "legTweenDuration",
              "type": "number",
              "value": 0.5
            }
          ]
        },
        {
          "name": "Customisation",
          "type": "structure",
          "children": [
            {
              "folded": true,
              "name": "body",
              "type": "number",
              "value": 0
            },
            {
              "folded": true,
              "name": "hand",
              "type": "number",
              "value": 0
            },
            {
              "folded": true,
              "name": "leg",
              "type": "number",
              "value": 0
            }
          ]
        }
      ],
      "effects": [],
      "behaviors": [
        {
          "name": "TopDownMovement",
          "type": "TopDownMovementBehavior::TopDownMovementBehavior",
          "acceleration": 400,
          "allowDiagonals": true,
          "angleOffset": 0,
          "angularMaxSpeed": 400,
          "customIsometryAngle": 30,
          "deceleration": 800,
          "ignoreDefaultControls": false,
          "maxSpeed": 200,
          "movementAngleOffset": 0,
          "rotateObject": true,
          "viewpoint": "TopDown"
        }
      ],
      "animations": [
        {
          "name": "",
          "useMultipleDirections": false,
          "directions": [
            {
              "looping": false,
              "timeBetweenFrames": 0.08,
              "sprites": [
                {
                  "hasCustomCollisionMask": true,
                  "image": "assets/character/body/body_1.png",
                  "points": [
                    {
                      "name": "pointR",
                      "x": 23,
                      "y": 48
                    },
                    {
                      "name": "pointL",
                      "x": 23,
                      "y": 18
                    }
                  ],
                  "originPoint": {
                    "name": "origine",
                    "x": 0,
                    "y": 0
                  },
                  "centerPoint": {
                    "automatic": true,
                    "name": "centre",
                    "x": 0,
                    "y": 0
                  },
                  "customCollisionMask": [
                    [
                      {
                        "x": 0,
                        "y": 0
                      },
                      {
                        "x": 44,
                        "y": 0
                      },
                      {
                        "x": 44,
                        "y": 66
                      },
                      {
                        "x": 0,
                        "y": 66
                      }
                    ]
                  ]
                }
              ]
            }
          ]
        },
        {
          "name": "",
          "useMultipleDirections": false,
          "directions": [
            {
              "looping": false,
              "timeBetweenFrames": 0.08,
              "sprites": [
                {
                  "hasCustomCollisionMask": true,
                  "image": "assets/character/body/body_2.png",
                  "points": [
                    {
                      "name": "pointR",
                      "x": 23,
                      "y": 48
                    },
                    {
                      "name": "pointL",
                      "x": 23,
                      "y": 18
                    }
                  ],
                  "originPoint": {
                    "name": "origine",
                    "x": 0,
                    "y": 0
                  },
                  "centerPoint": {
                    "automatic": true,
                    "name": "centre",
                    "x": 0,
                    "y": 0
                  },
                  "customCollisionMask": [
                    [
                      {
                        "x": 0,
                        "y": 0
                      },
                      {
                        "x": 44,
                        "y": 0
                      },
                      {
                        "x": 44,
                        "y": 66
                      },
                      {
                        "x": 0,
                        "y": 66
                      }
                    ]
                  ]
                }
              ]
            }
          ]
        },
        {
          "name": "",
          "useMultipleDirections": false,
          "directions": [
            {
              "looping": false,
              "timeBetweenFrames": 0.08,
              "sprites": [
                {
                  "hasCustomCollisionMask": true,
                  "image": "assets/character/body/body_3.png",
                  "points": [
                    {
                      "name": "pointR",
                      "x": 23,
                      "y": 48
                    },
                    {
                      "name": "pointL",
                      "x": 23,
                      "y": 18
                    }
                  ],
                  "originPoint": {
                    "name": "origine",
                    "x": 0,
                    "y": 0
                  },
                  "centerPoint": {
                    "automatic": true,
                    "name": "centre",
                    "x": 0,
                    "y": 0
                  },
                  "customCollisionMask": [
                    [
                      {
                        "x": 0,
                        "y": 0
                      },
                      {
                        "x": 44,
                        "y": 0
                      },
                      {
                        "x": 44,
                        "y": 66
                      },
                      {
                        "x": 0,
                        "y": 66
                      }
                    ]
                  ]
                }
              ]
            }
          ]
        },
        {
          "name": "",
          "useMultipleDirections": false,
          "directions": [
            {
              "looping": false,
              "timeBetweenFrames": 0.08,
              "sprites": [
                {
                  "hasCustomCollisionMask": true,
                  "image": "assets/character/body/body_4.png",
                  "points": [
                    {
                      "name": "pointR",
                      "x": 23,
                      "y": 48
                    },
                    {
                      "name": "pointL",
                      "x": 23,
                      "y": 18
                    }
                  ],
                  "originPoint": {
                    "name": "origine",
                    "x": 0,
                    "y": 0
                  },
                  "centerPoint": {
                    "automatic": true,
                    "name": "centre",
                    "x": 0,
                    "y": 0
                  },
                  "customCollisionMask": [
                    [
                      {
                        "x": 0,
                        "y": 0
                      },
                      {
                        "x": 44,
                        "y": 0
                      },
                      {
                        "x": 44,
                        "y": 66
                      },
                      {
                        "x": 0,
                        "y": 66
                      }
                    ]
                  ]
                }
              ]
            }
          ]
        },
        {
          "name": "",
          "useMultipleDirections": false,
          "directions": [
            {
              "looping": false,
              "timeBetweenFrames": 0.08,
              "sprites": [
                {
                  "hasCustomCollisionMask": true,
                  "image": "assets/character/body/body_5.png",
                  "points": [
                    {
                      "name": "pointR",
                      "x": 23,
                      "y": 48
                    },
                    {
                      "name": "pointL",
                      "x": 23,
                      "y": 18
                    }
                  ],
                  "originPoint": {
                    "name": "origine",
                    "x": 0,
                    "y": 0
                  },
                  "centerPoint": {
                    "automatic": true,
                    "name": "centre",
                    "x": 0,
                    "y": 0
                  },
                  "customCollisionMask": [
                    [
                      {
                        "x": 0,
                        "y": 0
                      },
                      {
                        "x": 44,
                        "y": 0
                      },
                      {
                        "x": 44,
                        "y": 66
                      },
                      {
                        "x": 0,
                        "y": 66
                      }
                    ]
                  ]
                }
              ]
            }
          ]
        },
        {
          "name": "",
          "useMultipleDirections": false,
          "directions": [
            {
              "looping": false,
              "timeBetweenFrames": 0.08,
              "sprites": [
                {
                  "hasCustomCollisionMask": true,
                  "image": "assets/character/body/body_6.png",
                  "points": [
                    {
                      "name": "pointR",
                      "x": 23,
                      "y": 48
                    },
                    {
                      "name": "pointL",
                      "x": 23,
                      "y": 18
                    }
                  ],
                  "originPoint": {
                    "name": "origine",
                    "x": 0,
                    "y": 0
                  },
                  "centerPoint": {
                    "automatic": true,
                    "name": "centre",
                    "x": 0,
                    "y": 0
                  },
                  "customCollisionMask": [
                    [
                      {
                        "x": 0,
                        "y": 0
                      },
                      {
                        "x": 44,
                        "y": 0
                      },
                      {
                        "x": 44,
                        "y": 66
                      },
                      {
                        "x": 0,
                        "y": 66
                      }
                    ]
                  ]
                }
              ]
            }
          ]
        },
        {
          "name": "",
          "useMultipleDirections": false,
          "directions": [
            {
              "looping": false,
              "timeBetweenFrames": 0.08,
              "sprites": [
                {
                  "hasCustomCollisionMask": true,
                  "image": "assets/character/body/body_7.png",
                  "points": [
                    {
                      "name": "pointR",
                      "x": 23,
                      "y": 48
                    },
                    {
                      "name": "pointL",
                      "x": 23,
                      "y": 18
                    }
                  ],
                  "originPoint": {
                    "name": "origine",
                    "x": 0,
                    "y": 0
                  },
                  "centerPoint": {
                    "automatic": true,
                    "name": "centre",
                    "x": 0,
                    "y": 0
                  },
                  "customCollisionMask": [
                    [
                      {
                        "x": 0,
                        "y": 0
                      },
                      {
                        "x": 44,
                        "y": 0
                      },
                      {
                        "x": 44,
                        "y": 66
                      },
                      {
                        "x": 0,
                        "y": 66
                      }
                    ]
                  ]
                }
              ]
            }
          ]
        },
        {
          "name": "",
          "useMultipleDirections": false,
          "directions": [
            {
              "looping": false,
              "timeBetweenFrames": 0.08,
              "sprites": [
                {
                  "hasCustomCollisionMask": true,
                  "image": "assets/character/body/body_8.png",
                  "points": [
                    {
                      "name": "pointR",
                      "x": 23,
                      "y": 48
                    },
                    {
                      "name": "pointL",
                      "x": 23,
                      "y": 18
                    }
                  ],
                  "originPoint": {
                    "name": "origine",
                    "x": 0,
                    "y": 0
                  },
                  "centerPoint": {
                    "automatic": true,
                    "name": "centre",
                    "x": 0,
                    "y": 0
                  },
                  "customCollisionMask": [
                    [
                      {
                        "x": 0,
                        "y": 0
                      },
                      {
                        "x": 44,
                        "y": 0
                      },
                      {
                        "x": 44,
                        "y": 66
                      },
                      {
                        "x": 0,
                        "y": 66
                      }
                    ]
                  ]
                }
              ]
            }
          ]
        },
        {
          "name": "",
          "useMultipleDirections": false,
          "directions": [
            {
              "looping": false,
              "timeBetweenFrames": 0.08,
              "sprites": [
                {
                  "hasCustomCollisionMask": true,
                  "image": "assets/character/body/body_9.png",
                  "points": [
                    {
                      "name": "pointR",
                      "x": 23,
                      "y": 48
                    },
                    {
                      "name": "pointL",
                      "x": 23,
                      "y": 18
                    }
                  ],
                  "originPoint": {
                    "name": "origine",
                    "x": 0,
                    "y": 0
                  },
                  "centerPoint": {
                    "automatic": true,
                    "name": "centre",
                    "x": 0,
                    "y": 0
                  },
                  "customCollisionMask": [
                    [
                      {
                        "x": 0,
                        "y": 0
                      },
                      {
                        "x": 44,
                        "y": 0
                      },
                      {
                        "x": 44,
                        "y": 66
                      },
                      {
                        "x": 0,
                        "y": 66
                      }
                    ]
                  ]
                }
              ]
            }
          ]
        }
      ]
    },
    {
      "adaptCollisionMaskAutomatically": true,
      "assetStoreId": "",
      "name": "player_leg",
      "type": "Sprite",
      "updateIfNotVisible": false,
      "variables": [
        {
          "folded": true,
          "name": "type",
          "type": "string",
          "value": ""
        },
        {
          "folded": true,
          "name": "angle",
          "type": "number",
          "value": 0
        }
      ],
      "effects": [],
      "behaviors": [
        {
          "name": "Tween",
          "type": "Tween::TweenBehavior"
        }
      ],
      "animations": [
        {
          "name": "",
          "useMultipleDirections": false,
          "directions": [
            {
              "looping": false,
              "timeBetweenFrames": 0.08,
              "sprites": [
                {
                  "hasCustomCollisionMask": true,
                  "image": "assets/character/leg/leg_5.png",
                  "points": [],
                  "originPoint": {
                    "name": "origine",
                    "x": 0,
                    "y": 15.5
                  },
                  "centerPoint": {
                    "automatic": false,
                    "name": "centre",
                    "x": 0,
                    "y": 15.5
                  },
                  "customCollisionMask": [
                    [
                      {
                        "x": 0,
                        "y": 0
                      },
                      {
                        "x": 39,
                        "y": 0
                      },
                      {
                        "x": 39,
                        "y": 28
                      },
                      {
                        "x": 0,
                        "y": 28
                      }
                    ]
                  ]
                }
              ]
            }
          ]
        },
        {
          "name": "",
          "useMultipleDirections": false,
          "directions": [
            {
              "looping": false,
              "timeBetweenFrames": 0.08,
              "sprites": [
                {
                  "hasCustomCollisionMask": true,
                  "image": "assets/character/leg/leg_6.png",
                  "points": [],
                  "originPoint": {
                    "name": "origine",
                    "x": 0,
                    "y": 15.5
                  },
                  "centerPoint": {
                    "automatic": false,
                    "name": "centre",
                    "x": 0,
                    "y": 15.5
                  },
                  "customCollisionMask": [
                    [
                      {
                        "x": 0,
                        "y": 0
                      },
                      {
                        "x": 39,
                        "y": 0
                      },
                      {
                        "x": 39,
                        "y": 28
                      },
                      {
                        "x": 0,
                        "y": 28
                      }
                    ]
                  ]
                }
              ]
            }
          ]
        },
        {
          "name": "",
          "useMultipleDirections": false,
          "directions": [
            {
              "looping": false,
              "timeBetweenFrames": 0.08,
              "sprites": [
                {
                  "hasCustomCollisionMask": true,
                  "image": "assets/character/leg/leg_2.png",
                  "points": [],
                  "originPoint": {
                    "name": "origine",
                    "x": 0,
                    "y": 15.5
                  },
                  "centerPoint": {
                    "automatic": false,
                    "name": "centre",
                    "x": 0,
                    "y": 15.5
                  },
                  "customCollisionMask": [
                    [
                      {
                        "x": 0,
                        "y": 0
                      },
                      {
                        "x": 39,
                        "y": 0
                      },
                      {
                        "x": 39,
                        "y": 28
                      },
                      {
                        "x": 0,
                        "y": 28
                      }
                    ]
                  ]
                }
              ]
            }
          ]
        },
        {
          "name": "",
          "useMultipleDirections": false,
          "directions": [
            {
              "looping": false,
              "timeBetweenFrames": 0.08,
              "sprites": [
                {
                  "hasCustomCollisionMask": true,
                  "image": "assets/character/leg/leg_1.png",
                  "points": [],
                  "originPoint": {
                    "name": "origine",
                    "x": 0,
                    "y": 15.5
                  },
                  "centerPoint": {
                    "automatic": false,
                    "name": "centre",
                    "x": 0,
                    "y": 15.5
                  },
                  "customCollisionMask": [
                    [
                      {
                        "x": 0,
                        "y": 0
                      },
                      {
                        "x": 39,
                        "y": 0
                      },
                      {
                        "x": 39,
                        "y": 28
                      },
                      {
                        "x": 0,
                        "y": 28
                      }
                    ]
                  ]
                }
              ]
            }
          ]
        },
        {
          "name": "",
          "useMultipleDirections": false,
          "directions": [
            {
              "looping": false,
              "timeBetweenFrames": 0.08,
              "sprites": [
                {
                  "hasCustomCollisionMask": true,
                  "image": "assets/character/leg/leg_3.png",
                  "points": [],
                  "originPoint": {
                    "name": "origine",
                    "x": 0,
                    "y": 15.5
                  },
                  "centerPoint": {
                    "automatic": false,
                    "name": "centre",
                    "x": 0,
                    "y": 15.5
                  },
                  "customCollisionMask": [
                    [
                      {
                        "x": 0,
                        "y": 0
                      },
                      {
                        "x": 39,
                        "y": 0
                      },
                      {
                        "x": 39,
                        "y": 28
                      },
                      {
                        "x": 0,
                        "y": 28
                      }
                    ]
                  ]
                }
              ]
            }
          ]
        },
        {
          "name": "",
          "useMultipleDirections": false,
          "directions": [
            {
              "looping": false,
              "timeBetweenFrames": 0.08,
              "sprites": [
                {
                  "hasCustomCollisionMask": true,
                  "image": "assets/character/leg/leg_4.png",
                  "points": [],
                  "originPoint": {
                    "name": "origine",
                    "x": 0,
                    "y": 15.5
                  },
                  "centerPoint": {
                    "automatic": false,
                    "name": "centre",
                    "x": 0,
                    "y": 15.5
                  },
                  "customCollisionMask": [
                    [
                      {
                        "x": 0,
                        "y": 0
                      },
                      {
                        "x": 39,
                        "y": 0
                      },
                      {
                        "x": 39,
                        "y": 28
                      },
                      {
                        "x": 0,
                        "y": 28
                      }
                    ]
                  ]
                }
              ]
            }
          ]
        },
        {
          "name": "",
          "useMultipleDirections": false,
          "directions": [
            {
              "looping": false,
              "timeBetweenFrames": 0.08,
              "sprites": [
                {
                  "hasCustomCollisionMask": true,
                  "image": "assets/character/leg/leg_8.png",
                  "points": [],
                  "originPoint": {
                    "name": "origine",
                    "x": 0,
                    "y": 15.5
                  },
                  "centerPoint": {
                    "automatic": false,
                    "name": "centre",
                    "x": 0,
                    "y": 15.5
                  },
                  "customCollisionMask": [
                    [
                      {
                        "x": 0,
                        "y": 0
                      },
                      {
                        "x": 39,
                        "y": 0
                      },
                      {
                        "x": 39,
                        "y": 28
                      },
                      {
                        "x": 0,
                        "y": 28
                      }
                    ]
                  ]
                }
              ]
            }
          ]
        },
        {
          "name": "",
          "useMultipleDirections": false,
          "directions": [
            {
              "looping": false,
              "timeBetweenFrames": 0.08,
              "sprites": [
                {
                  "hasCustomCollisionMask": true,
                  "image": "assets/character/leg/leg_7.png",
                  "points": [],
                  "originPoint": {
                    "name": "origine",
                    "x": 0,
                    "y": 15.5
                  },
                  "centerPoint": {
                    "automatic": false,
                    "name": "centre",
                    "x": 0,
                    "y": 15.5
                  },
                  "customCollisionMask": [
                    [
                      {
                        "x": 0,
                        "y": 0
                      },
                      {
                        "x": 39,
                        "y": 0
                      },
                      {
                        "x": 39,
                        "y": 28
                      },
                      {
                        "x": 0,
                        "y": 28
                      }
                    ]
                  ]
                }
              ]
            }
          ]
        }
      ]
    },
    {
      "adaptCollisionMaskAutomatically": true,
      "assetStoreId": "",
      "name": "player_hand",
      "type": "Sprite",
      "updateIfNotVisible": false,
      "variables": [
        {
          "folded": true,
          "name": "type",
          "type": "string",
          "value": ""
        },
        {
          "folded": true,
          "name": "angle",
          "type": "number",
          "value": 0
        }
      ],
      "effects": [],
      "behaviors": [
        {
          "name": "Tween",
          "type": "Tween::TweenBehavior"
        }
      ],
      "animations": [
        {
          "name": "",
          "useMultipleDirections": false,
          "directions": [
            {
              "looping": false,
              "timeBetweenFrames": 0.08,
              "sprites": [
                {
                  "hasCustomCollisionMask": true,
                  "image": "assets/character/hand/hand_2.png",
                  "points": [],
                  "originPoint": {
                    "name": "origine",
                    "x": 0,
                    "y": 15.5
                  },
                  "centerPoint": {
                    "automatic": false,
                    "name": "centre",
                    "x": 0,
                    "y": 15.5
                  },
                  "customCollisionMask": [
                    [
                      {
                        "x": 0,
                        "y": 0
                      },
                      {
                        "x": 39,
                        "y": 0
                      },
                      {
                        "x": 39,
                        "y": 24
                      },
                      {
                        "x": 0,
                        "y": 24
                      }
                    ]
                  ]
                }
              ]
            }
          ]
        },
        {
          "name": "",
          "useMultipleDirections": false,
          "directions": [
            {
              "looping": false,
              "timeBetweenFrames": 0.08,
              "sprites": [
                {
                  "hasCustomCollisionMask": true,
                  "image": "assets/character/hand/hand_1.png",
                  "points": [],
                  "originPoint": {
                    "name": "origine",
                    "x": 0,
                    "y": 15.5
                  },
                  "centerPoint": {
                    "automatic": false,
                    "name": "centre",
                    "x": 0,
                    "y": 15.5
                  },
                  "customCollisionMask": [
                    [
                      {
                        "x": 0,
                        "y": 0
                      },
                      {
                        "x": 39,
                        "y": 0
                      },
                      {
                        "x": 39,
                        "y": 24
                      },
                      {
                        "x": 0,
                        "y": 24
                      }
                    ]
                  ]
                }
              ]
            }
          ]
        },
        {
          "name": "",
          "useMultipleDirections": false,
          "directions": [
            {
              "looping": false,
              "timeBetweenFrames": 0.08,
              "sprites": [
                {
                  "hasCustomCollisionMask": true,
                  "image": "assets/character/hand/hand_3.png",
                  "points": [],
                  "originPoint": {
                    "name": "origine",
                    "x": 0,
                    "y": 15.5
                  },
                  "centerPoint": {
                    "automatic": false,
                    "name": "centre",
                    "x": 0,
                    "y": 15.5
                  },
                  "customCollisionMask": [
                    [
                      {
                        "x": 0,
                        "y": 0
                      },
                      {
                        "x": 39,
                        "y": 0
                      },
                      {
                        "x": 39,
                        "y": 24
                      },
                      {
                        "x": 0,
                        "y": 24
                      }
                    ]
                  ]
                }
              ]
            }
          ]
        },
        {
          "name": "",
          "useMultipleDirections": false,
          "directions": [
            {
              "looping": false,
              "timeBetweenFrames": 0.08,
              "sprites": [
                {
                  "hasCustomCollisionMask": true,
                  "image": "assets/character/hand/hand_4.png",
                  "points": [],
                  "originPoint": {
                    "name": "origine",
                    "x": 0,
                    "y": 15.5
                  },
                  "centerPoint": {
                    "automatic": false,
                    "name": "centre",
                    "x": 0,
                    "y": 15.5
                  },
                  "customCollisionMask": [
                    [
                      {
                        "x": 0,
                        "y": 0
                      },
                      {
                        "x": 39,
                        "y": 0
                      },
                      {
                        "x": 39,
                        "y": 24
                      },
                      {
                        "x": 0,
                        "y": 24
                      }
                    ]
                  ]
                }
              ]
            }
          ]
        },
        {
          "name": "",
          "useMultipleDirections": false,
          "directions": [
            {
              "looping": false,
              "timeBetweenFrames": 0.08,
              "sprites": [
                {
                  "hasCustomCollisionMask": true,
                  "image": "assets/character/hand/hand_5.png",
                  "points": [],
                  "originPoint": {
                    "name": "origine",
                    "x": 0,
                    "y": 15.5
                  },
                  "centerPoint": {
                    "automatic": false,
                    "name": "centre",
                    "x": 0,
                    "y": 15.5
                  },
                  "customCollisionMask": [
                    [
                      {
                        "x": 0,
                        "y": 0
                      },
                      {
                        "x": 39,
                        "y": 0
                      },
                      {
                        "x": 39,
                        "y": 24
                      },
                      {
                        "x": 0,
                        "y": 24
                      }
                    ]
                  ]
                }
              ]
            }
          ]
        },
        {
          "name": "",
          "useMultipleDirections": false,
          "directions": [
            {
              "looping": false,
              "timeBetweenFrames": 0.08,
              "sprites": [
                {
                  "hasCustomCollisionMask": true,
                  "image": "assets/character/hand/hand_6.png",
                  "points": [],
                  "originPoint": {
                    "name": "origine",
                    "x": 0,
                    "y": 15.5
                  },
                  "centerPoint": {
                    "automatic": false,
                    "name": "centre",
                    "x": 0,
                    "y": 15.5
                  },
                  "customCollisionMask": [
                    [
                      {
                        "x": 0,
                        "y": 0
                      },
                      {
                        "x": 39,
                        "y": 0
                      },
                      {
                        "x": 39,
                        "y": 24
                      },
                      {
                        "x": 0,
                        "y": 24
                      }
                    ]
                  ]
                }
              ]
            }
          ]
        },
        {
          "name": "",
          "useMultipleDirections": false,
          "directions": [
            {
              "looping": false,
              "timeBetweenFrames": 0.08,
              "sprites": [
                {
                  "hasCustomCollisionMask": true,
                  "image": "assets/character/hand/hand_7.png",
                  "points": [],
                  "originPoint": {
                    "name": "origine",
                    "x": 0,
                    "y": 15.5
                  },
                  "centerPoint": {
                    "automatic": false,
                    "name": "centre",
                    "x": 0,
                    "y": 15.5
                  },
                  "customCollisionMask": [
                    [
                      {
                        "x": 0,
                        "y": 0
                      },
                      {
                        "x": 39,
                        "y": 0
                      },
                      {
                        "x": 39,
                        "y": 24
                      },
                      {
                        "x": 0,
                        "y": 24
                      }
                    ]
                  ]
                }
              ]
            }
          ]
        },
        {
          "name": "",
          "useMultipleDirections": false,
          "directions": [
            {
              "looping": false,
              "timeBetweenFrames": 0.08,
              "sprites": [
                {
                  "hasCustomCollisionMask": true,
                  "image": "assets/character/hand/hand_8.png",
                  "points": [],
                  "originPoint": {
                    "name": "origine",
                    "x": 0,
                    "y": 15.5
                  },
                  "centerPoint": {
                    "automatic": false,
                    "name": "centre",
                    "x": 0,
                    "y": 15.5
                  },
                  "customCollisionMask": [
                    [
                      {
                        "x": 0,
                        "y": 0
                      },
                      {
                        "x": 39,
                        "y": 0
                      },
                      {
                        "x": 39,
                        "y": 24
                      },
                      {
                        "x": 0,
                        "y": 24
                      }
                    ]
                  ]
                }
              ]
            }
          ]
        },
        {
          "name": "",
          "useMultipleDirections": false,
          "directions": [
            {
              "looping": false,
              "timeBetweenFrames": 0.08,
              "sprites": [
                {
                  "hasCustomCollisionMask": true,
                  "image": "assets/character/hand/hand_9.png",
                  "points": [],
                  "originPoint": {
                    "name": "origine",
                    "x": 0,
                    "y": 15.5
                  },
                  "centerPoint": {
                    "automatic": false,
                    "name": "centre",
                    "x": 0,
                    "y": 15.5
                  },
                  "customCollisionMask": [
                    [
                      {
                        "x": 0,
                        "y": 0
                      },
                      {
                        "x": 39,
                        "y": 0
                      },
                      {
                        "x": 39,
                        "y": 24
                      },
                      {
                        "x": 0,
                        "y": 24
                      }
                    ]
                  ]
                }
              ]
            }
          ]
        },
        {
          "name": "",
          "useMultipleDirections": false,
          "directions": [
            {
              "looping": false,
              "timeBetweenFrames": 0.08,
              "sprites": [
                {
                  "hasCustomCollisionMask": true,
                  "image": "assets/character/hand/hand_10.png",
                  "points": [],
                  "originPoint": {
                    "name": "origine",
                    "x": 0,
                    "y": 15.5
                  },
                  "centerPoint": {
                    "automatic": false,
                    "name": "centre",
                    "x": 0,
                    "y": 15.5
                  },
                  "customCollisionMask": [
                    [
                      {
                        "x": 0,
                        "y": 0
                      },
                      {
                        "x": 39,
                        "y": 0
                      },
                      {
                        "x": 39,
                        "y": 24
                      },
                      {
                        "x": 0,
                        "y": 24
                      }
                    ]
                  ]
                }
              ]
            }
          ]
        }
      ]
    },
    {
      "assetStoreId": "bfeeb465a4a164b560a2215e3ff9e78e66123af43cbf7ef1f22d56fca4271c80",
      "name": "SquareWhiteSlider",
      "type": "PanelSpriteSlider::PanelSpriteSlider",
      "variables": [],
      "effects": [],
      "behaviors": [],
      "content": {
        "BarTopPadding": 6,
        "BarLeftPadding": 6,
        "BarRightPadding": 6,
        "BarBottomPadding": 6,
        "LabelMargin": 6,
        "MaxValue": 3,
        "InitialValue": 0
      },
      "childrenContent": {
        "Background": {
          "bottomMargin": 4,
          "height": 28,
          "leftMargin": 2,
          "rightMargin": 2,
          "texture": "assets/UI/bar/Square White Slider Border.png",
          "tiled": false,
          "topMargin": 4,
          "width": 265
        },
        "FillBar": {
          "bottomMargin": 2,
          "height": 16,
          "leftMargin": 0,
          "rightMargin": 0,
          "texture": "assets/UI/bar/Square White Slider Fill Bar.png",
          "tiled": false,
          "topMargin": 0,
          "width": 16
        },
        "Label": {
          "bold": false,
          "italic": false,
          "smoothed": true,
          "underlined": false,
          "string": "It displays the value when it changes.",
          "font": "",
          "textAlignment": "",
          "characterSize": 20,
          "color": {
            "b": 221,
            "g": 221,
            "r": 221
          },
          "content": {
            "bold": false,
            "isOutlineEnabled": false,
            "isShadowEnabled": false,
            "italic": false,
            "outlineColor": "255;255;255",
            "outlineThickness": 2,
            "shadowAngle": 90,
            "shadowBlurRadius": 2,
            "shadowColor": "0;0;0",
            "shadowDistance": 4,
            "shadowOpacity": 127,
            "smoothed": true,
            "underlined": false,
            "text": "It displays the value when it changes.",
            "font": "",
            "textAlignment": "",
            "characterSize": 20,
            "color": "221;221;221"
          }
        },
        "Thumb": {
          "bottomMargin": 2,
          "height": 36,
          "leftMargin": 1,
          "rightMargin": 1,
          "texture": "assets/UI/bar/Square White Slider Thumb.png",
          "tiled": false,
          "topMargin": 2,
          "width": 22
        }
      }
    },
    {
      "assetStoreId": "d907b5df38595e6d3f128058fbb3dbd0861f86505cc6d7bf9859ddcc3eceeb1f",
      "name": "WhiteDecoratedButton",
      "type": "PanelSpriteButton::PanelSpriteButton",
      "variables": [],
      "effects": [],
      "behaviors": [],
      "content": {
        "LeftPadding": 16,
        "RightPadding": 16,
        "PressedLabelOffsetY": 6,
        "BottomPadding": 24,
        "TopPadding": 20,
        "HoveredFadeOutDuration": 0.25
      },
      "childrenContent": {
        "Hovered": {
          "bottomMargin": 22,
          "height": 64,
          "leftMargin": 16,
          "rightMargin": 16,
          "texture": "assets/UI/button/White Decorated Button_Hovered.png",
          "tiled": true,
          "topMargin": 16,
          "width": 192
        },
        "Idle": {
          "bottomMargin": 22,
          "height": 64,
          "leftMargin": 16,
          "rightMargin": 16,
          "texture": "assets/UI/button/White Decorated Button_Idle.png",
          "tiled": true,
          "topMargin": 16,
          "width": 192
        },
        "Label": {
          "bold": false,
          "italic": false,
          "smoothed": true,
          "underlined": false,
          "string": "Start",
          "font": "ArchitectsDaughter.ttf",
          "textAlignment": "center",
          "characterSize": 16,
          "color": {
            "b": 0,
            "g": 0,
            "r": 0
          },
          "content": {
            "bold": false,
            "isOutlineEnabled": false,
            "isShadowEnabled": false,
            "italic": false,
            "outlineColor": "255;255;255",
            "outlineThickness": 2,
            "shadowAngle": 90,
            "shadowBlurRadius": 2,
            "shadowColor": "0;0;0",
            "shadowDistance": 4,
            "shadowOpacity": 127,
            "smoothed": true,
            "underlined": false,
            "text": "Start",
            "font": "ArchitectsDaughter.ttf",
            "textAlignment": "center",
            "characterSize": 16,
            "color": "0;0;0"
          }
        },
        "Pressed": {
          "bottomMargin": 16,
          "height": 64,
          "leftMargin": 16,
          "rightMargin": 16,
          "texture": "assets/UI/button/White Decorated Button_Pressed.png",
          "tiled": true,
          "topMargin": 22,
          "width": 192
        }
      }
    }
  ],
  "objectsFolderStructure": {
    "folderName": "__ROOT",
    "children": [
      {
        "folderName": "Player",
        "children": [
          {
            "objectName": "player_leg"
          },
          {
            "objectName": "player_hand"
          },
          {
            "objectName": "player_body"
          }
        ]
      },
      {
        "objectName": "SquareWhiteSlider"
      },
      {
        "objectName": "WhiteDecoratedButton"
      }
    ]
  },
  "events": [
    {
      "type": "BuiltinCommonInstructions::Standard",
      "conditions": [],
      "actions": [
        {
          "type": {
            "value": "AnimatableCapability::AnimatableBehavior::SetIndex"
          },
          "parameters": [
            "player_body",
            "Animation",
            "=",
            "SquareWhiteSlider.Value() "
          ]
        },
        {
          "type": {
            "value": "AnimatableCapability::AnimatableBehavior::SetIndex"
          },
          "parameters": [
            "player_hand",
            "Animation",
            "=",
            "SquareWhiteSlider.Value()"
          ]
        },
        {
          "type": {
            "value": "AnimatableCapability::AnimatableBehavior::SetIndex"
          },
          "parameters": [
            "player_leg",
            "Animation",
            "=",
            "SquareWhiteSlider.Value()"
          ]
        }
      ]
    },
    {
      "type": "BuiltinCommonInstructions::Standard",
      "conditions": [],
      "actions": [
        {
          "type": {
            "value": "ModVarGlobal"
          },
          "parameters": [
            "Player.Customisation.body",
            "=",
            "player_body.Animation::Index()"
          ]
        },
        {
          "type": {
            "value": "ModVarGlobal"
          },
          "parameters": [
            "Player.Customisation.hand",
            "=",
            "player_hand.Animation::Index()"
          ]
        },
        {
          "type": {
            "value": "ModVarGlobal"
          },
          "parameters": [
            "Player.Customisation.leg",
            "=",
            "player_leg.Animation::Index()"
          ]
        }
      ]
    },
    {
      "type": "BuiltinCommonInstructions::Standard",
      "conditions": [
        {
          "type": {
            "value": "PanelSpriteButton::PanelSpriteButton::IsClicked"
          },
          "parameters": [
            "WhiteDecoratedButton",
            ""
          ]
        }
      ],
      "actions": [
        {
          "type": {
            "value": "Scene"
          },
          "parameters": [
            "",
            "\"Game_Map\"",
            ""
          ]
        }
      ]
    }
  ],
  "layers": [
    {
      "ambientLightColorB": 200,
      "ambientLightColorG": 200,
      "ambientLightColorR": 200,
      "camera3DFarPlaneDistance": 10000,
      "camera3DFieldOfView": 45,
      "camera3DNearPlaneDistance": 3,
      "cameraType": "",
      "followBaseLayerCamera": false,
      "isLightingLayer": false,
      "isLocked": false,
      "name": "",
      "renderingType": "",
      "visibility": true,
      "cameras": [
        {
          "defaultSize": true,
          "defaultViewport": true,
          "height": 0,
          "viewportBottom": 1,
          "viewportLeft": 0,
          "viewportRight": 1,
          "viewportTop": 0,
          "width": 0
        }
      ],
      "effects": [
        {
          "effectType": "Scene3D::HemisphereLight",
          "name": "3D Light",
          "doubleParameters": {
            "elevation": 45,
            "intensity": 1,
            "rotation": 0
          },
          "stringParameters": {
            "groundColor": "64;64;64",
            "skyColor": "255;255;255",
            "top": "Y-"
          },
          "booleanParameters": {}
        }
      ]
    }
  ],
  "behaviorsSharedData": [
    {
      "name": "Animation",
      "type": "AnimatableCapability::AnimatableBehavior"
    },
    {
      "name": "Effect",
      "type": "EffectCapability::EffectBehavior"
    },
    {
      "name": "FlashTransitionPainter",
      "type": "FlashTransitionPainter::FlashTransitionPainter"
    },
    {
      "name": "Flippable",
      "type": "FlippableCapability::FlippableBehavior"
    },
    {
      "name": "Opacity",
      "type": "OpacityCapability::OpacityBehavior"
    },
    {
      "name": "Resizable",
      "type": "ResizableCapability::ResizableBehavior"
    },
    {
      "name": "Scale",
      "type": "ScalableCapability::ScalableBehavior"
    },
    {
      "name": "TopDownMovement",
      "type": "TopDownMovementBehavior::TopDownMovementBehavior"
    },
    {
      "name": "Tween",
      "type": "Tween::TweenBehavior"
    }
  ]
}